{"FullTypeName":"FFXIVClientStructs.FFXIV.Client.Game.QuestManager","Name":"QuestManager","Pattern":"E8 ?? ?? ?? ?? 66 BA 10 0C","Vars":{"_normalQuests":{"Offset":16,"Type":"QuestWork","ArraySize":30},"_dailyQuests":{"Offset":1496,"Type":"DailyQuestWork","ArraySize":12},"_trackedQuests":{"Offset":1736,"Type":"TrackingWork","ArraySize":5},"_beastReputation":{"Offset":3144,"Type":"BeastReputationWork","ArraySize":17},"_leveQuests":{"Offset":3416,"Type":"LeveWork","ArraySize":16},"NumLeveAllowances":{"Offset":3800,"Type":"byte","ArraySize":1},"NumAcceptedQuests":{"Offset":4040,"Type":"byte","ArraySize":1}}}